packagerit/__init__.py
packagerit-0.1.dist-info/METADATA
packagerit-0.1.dist-info/WHEEL
packagerit-0.1.dist-info/top_level.txt
packagerit-0.1.dist-info/RECORD
