Metadata-Version: 2.1
Name: packagerit
Version: 0.1
Summary: this package packages Rit
Home-page: UNKNOWN
Author: Rit Chowdhury
Author-email: UNKNOWN
License: UNKNOWN
Platform: UNKNOWN
